fashion_mnist_ore_shard01/__init__.py
fashion_mnist_ore_shard01/shard-01.bin
fashion_mnist_ore_shard01-0.1.0.dist-info/METADATA
fashion_mnist_ore_shard01-0.1.0.dist-info/WHEEL
fashion_mnist_ore_shard01-0.1.0.dist-info/top_level.txt
fashion_mnist_ore_shard01-0.1.0.dist-info/RECORD
