Metadata-Version: 2.4
Name: fashion-mnist-ore-shard01
Version: 0.1.0
Summary: Shard 01 for fashion-mnist-ore
Author: OREYH
Requires-Python: >=3.8
